passaosfriday/FileService.py
passaosfriday/__init__.py
passaosfriday-1.0.1.dist-info/METADATA
passaosfriday-1.0.1.dist-info/WHEEL
passaosfriday-1.0.1.dist-info/top_level.txt
passaosfriday-1.0.1.dist-info/RECORD
