Metadata-Version: 2.1
Name: passaosfriday
Version: 1.0.1
Summary: 签名数据封装
Home-page: https://github.com/longweiqiang/dada_openapi_python
Author: mengying
Classifier: Programming Language :: Python :: 3
Classifier: License :: OSI Approved :: MIT License
Classifier: Operating System :: OS Independent
Requires-Python: >=3.6
Requires-Dist: requests (==2.27.1)
